s1db/__init__.py
s1db-1.0.3.dist-info/METADATA
s1db-1.0.3.dist-info/WHEEL
s1db-1.0.3.dist-info/top_level.txt
s1db-1.0.3.dist-info/zip-safe
s1db-1.0.3.dist-info/RECORD
